__init__.py
qosd.py
qosd-20230530.dist-info/METADATA
qosd-20230530.dist-info/WHEEL
qosd-20230530.dist-info/entry_points.txt
qosd-20230530.dist-info/top_level.txt
qosd-20230530.dist-info/RECORD
