Metadata-Version: 2.1
Name: qosd
Version: 20230530
Summary: QOSD for python
Author-email: Laurent Ghigonis <ooookiwi@gmail.com>
License: BSD-3-Clause
Project-URL: Homepage, https://github.com/looran/qosd
Keywords: osd,on-screen-display,tail
Requires-Python: >=3.0
Requires-Dist: pyside6
Requires-Dist: importlib-metadata ; python_version < "3.8"
